MANIFEST.in
README
setup.py
django_multilingual_ng.egg-info/PKG-INFO
django_multilingual_ng.egg-info/SOURCES.txt
django_multilingual_ng.egg-info/dependency_links.txt
django_multilingual_ng.egg-info/not-zip-safe
django_multilingual_ng.egg-info/top_level.txt
multilingual/__init__.py
multilingual/admin.py
multilingual/compiler.py
multilingual/context_processors.py
multilingual/exceptions.py
multilingual/fields.py
multilingual/languages.py
multilingual/manager.py
multilingual/middleware.py
multilingual/models.py
multilingual/query.py
multilingual/settings.py
multilingual/translation.py
multilingual/utils.py
multilingual/validation.py
multilingual/flatpages/__init__.py
multilingual/flatpages/admin.py
multilingual/flatpages/middleware.py
multilingual/flatpages/models.py
multilingual/flatpages/urls.py
multilingual/flatpages/views.py
multilingual/flatpages/templates/flatpages/default.html
multilingual/management/__init__.py
multilingual/management/commands/__init__.py
multilingual/management/commands/mlng_convert.py
multilingual/media/multilingual/admin/css/style.css
multilingual/templates/admin/edit_inline_translations.html
multilingual/templates/admin/edit_inline_translations_newforms.html
multilingual/templates/admin/fieldset.html
multilingual/templates/admin/multilingual/change_form.html
multilingual/templates/admin/multilingual/edit_inline/tabular.html
multilingual/templatetags/__init__.py
multilingual/templatetags/multilingual_tags.py
tests/__init__.py
tests/bootstrap.py
tests/testproject/__init__.py
tests/testproject/models.py
tests/testproject/settings.py
tests/testproject/urls.py
tests/testproject/tests/__init__.py
tests/testproject/tests/core.py
tests/testproject/tests/flatpages.py
tests/testproject/tests/templates.py