Metadata-Version: 1.0
Name: django-multilingual-ng
Version: 0.1.20
Summary: Multilingual extension for Django - NG
Home-page: http://github.com/ojii/django-multilingual-ng
Author: Jonas Obrist
Author-email: UNKNOWN
License: UNKNOWN
Platform: UNKNOWN
